onnxdumper/__init__.py
onnxdumper/dumper.py
onnxdumper-0.7.dist-info/METADATA
onnxdumper-0.7.dist-info/WHEEL
onnxdumper-0.7.dist-info/top_level.txt
onnxdumper-0.7.dist-info/RECORD
