Metadata-Version: 2.1
Name: onnxdumper
Version: 0.7
Summary: A package for ONNX intermediate data dumping
Home-page: UNKNOWN
Author: Souls-R
Author-email: 2362912722@qq.com
License: UNKNOWN
Platform: UNKNOWN
Classifier: Programming Language :: Python :: 3
Classifier: License :: OSI Approved :: MIT License
Classifier: Operating System :: OS Independent
Requires-Python: >=3.6
Requires-Dist: numpy
Requires-Dist: onnx
Requires-Dist: onnxruntime
